pypersiandate/__init__.py
pypersiandate/pypersiandate.py
pypersiandate-0.0.4.dist-info/LICENSE
pypersiandate-0.0.4.dist-info/METADATA
pypersiandate-0.0.4.dist-info/WHEEL
pypersiandate-0.0.4.dist-info/top_level.txt
pypersiandate-0.0.4.dist-info/RECORD
