Metadata-Version: 2.1
Name: pypersiandate
Version: 0.0.4
Summary: Python library for converting gregorian date to persian date.
Home-page: https://github.com/Hamed-Ghasemi/pypersiandate
Author: Hamed Ghasemi
Author-email: hamed.ghasemi.gl@gmail.com
License: MIT
Platform: UNKNOWN
